kimsufichecker/__init__.py
kimsufichecker/cli.py
kimsufichecker-1.1.0.dist-info/entry_points.txt
kimsufichecker-1.1.0.dist-info/LICENSE
kimsufichecker-1.1.0.dist-info/WHEEL
kimsufichecker-1.1.0.dist-info/METADATA
kimsufichecker-1.1.0.dist-info/RECORD
