Metadata-Version: 2.1
Name: kimsufichecker
Version: 1.1.0
Summary: Command line tool to monitor Kimsufi plans availability
Home-page: https://github.com/essembeh/kimsufi-checker
License: Apache-2.0
Author: Sébastien MB
Author-email: seb@essembeh.org
Requires-Python: >=3.6,<4.0
Classifier: Development Status :: 4 - Beta
Classifier: License :: OSI Approved :: Apache Software License
Classifier: Programming Language :: Python :: 3
Classifier: Programming Language :: Python :: 3.6
Classifier: Programming Language :: Python :: 3.7
Classifier: Programming Language :: Python :: 3.8
Classifier: Programming Language :: Python :: 3.9
Classifier: Topic :: Utilities
Requires-Dist: colorama
Requires-Dist: importlib_metadata; python_version < "3.8"
Requires-Dist: requests
